gdpython/__init__.py
gdpython/core.py
gdpython/game.py
gdpython/objects.py
gdpython-0.1.1.dist-info/LICENSE
gdpython-0.1.1.dist-info/METADATA
gdpython-0.1.1.dist-info/WHEEL
gdpython-0.1.1.dist-info/top_level.txt
gdpython-0.1.1.dist-info/RECORD
