Metadata-Version: 2.2
Name: gdpython
Version: 0.1.1
Summary: GDPython ist eine QT6/Python basierte Game Engine für die einfache Erstellung von 2D-Spielen.
Home-page: https://github.com/Michael0992/GDPython
Author: Michael Lutz
Author-email: michel.lutz92@gmail.com
Classifier: Programming Language :: Python :: 3
Classifier: License :: OSI Approved :: MIT License
Classifier: Operating System :: OS Independent
Classifier: Intended Audience :: Developers
Classifier: Topic :: Software Development :: Libraries :: Python Modules
Requires-Python: >=3.6
License-File: LICENSE
Requires-Dist: PyQt6==6.8.1
Requires-Dist: PyQt6-Qt6==6.8.2
Requires-Dist: PyQt6_sip==13.10.0
Dynamic: author
Dynamic: author-email
Dynamic: classifier
Dynamic: description
Dynamic: description-content-type
Dynamic: home-page
Dynamic: requires-dist
Dynamic: requires-python
Dynamic: summary
